torch_state_bridge/__init__.py
torch_state_bridge-0.1.0.dist-info/WHEEL
torch_state_bridge-0.1.0.dist-info/METADATA
torch_state_bridge-0.1.0.dist-info/RECORD
