Metadata-Version: 2.3
Name: torch-state-bridge
Version: 0.1.0
Summary: A powerful library for transforming PyTorch state dict keys with rule-based mappings, arithmetic operations, and advanced transformations.
Author: dummyjenil
Author-email: dummyjenil <dummyjenil@gmail.com>
